jupyterlite_pyodide_kernel/__init__.py
jupyterlite_pyodide_kernel/_version.py
jupyterlite_pyodide_kernel/app.py
jupyterlite_pyodide_kernel/constants.py
jupyterlite_pyodide_kernel/addons/__init__.py
jupyterlite_pyodide_kernel/addons/_base.py
jupyterlite_pyodide_kernel/addons/piplite.py
jupyterlite_pyodide_kernel/addons/pyodide.py
jupyterlite_pyodide_kernel/tests/__init__.py
jupyterlite_pyodide_kernel/tests/conftest.py
jupyterlite_pyodide_kernel/tests/test_metadata.py
jupyterlite_pyodide_kernel/tests/test_piplite.py
jupyterlite_pyodide_kernel/tests/test_pyodide.py
jupyterlite_pyodide_kernel/tests/test_repo.py
jupyterlite_pyodide_kernel/tests/fixtures/the_smallest_extension-0.1.0-py3-none-any.whl
jupyterlite_pyodide_kernel-0.6.0.data/data/share/jupyter/labextensions/@jupyterlite/pyodide-kernel-extension/package.json
jupyterlite_pyodide_kernel-0.6.0.data/data/share/jupyter/labextensions/@jupyterlite/pyodide-kernel-extension/static/112.161fc2b03668eb42acd9.js
jupyterlite_pyodide_kernel-0.6.0.data/data/share/jupyter/labextensions/@jupyterlite/pyodide-kernel-extension/static/112.161fc2b03668eb42acd9.js.LICENSE.txt
jupyterlite_pyodide_kernel-0.6.0.data/data/share/jupyter/labextensions/@jupyterlite/pyodide-kernel-extension/static/112.161fc2b03668eb42acd9.js.map
jupyterlite_pyodide_kernel-0.6.0.data/data/share/jupyter/labextensions/@jupyterlite/pyodide-kernel-extension/static/154.0d17684eb47a7d45e0a9.js
jupyterlite_pyodide_kernel-0.6.0.data/data/share/jupyter/labextensions/@jupyterlite/pyodide-kernel-extension/static/154.0d17684eb47a7d45e0a9.js.map
jupyterlite_pyodide_kernel-0.6.0.data/data/share/jupyter/labextensions/@jupyterlite/pyodide-kernel-extension/static/304.fed478b20183b113f417.js
jupyterlite_pyodide_kernel-0.6.0.data/data/share/jupyter/labextensions/@jupyterlite/pyodide-kernel-extension/static/304.fed478b20183b113f417.js.LICENSE.txt
jupyterlite_pyodide_kernel-0.6.0.dist-info/METADATA
jupyterlite_pyodide_kernel-0.6.0.dist-info/WHEEL
jupyterlite_pyodide_kernel-0.6.0.dist-info/entry_points.txt
jupyterlite_pyodide_kernel-0.6.0.dist-info/licenses/LICENSE
jupyterlite_pyodide_kernel-0.6.0.dist-info/RECORD
