Metadata-Version: 2.4
Name: jupyterlite-pyodide-kernel
Version: 0.6.0
Summary: Python kernel for JupyterLite powered by Pyodide
Project-URL: Homepage, https://jupyterlite-pyodide-kernel.readthedocs.io
Project-URL: Documentation, https://jupyterlite-pyodide-kernel.readthedocs.io
Project-URL: Source, https://github.com/jupyterlite/pyodide-kernel
Project-URL: Issues, https://github.com/jupyterlite/pyodide-kernel/issues
Project-URL: PyPI, https://pypi.org/project/jupyterlite-pyodide-kernel
Author: JupyterLite Contributors
License: BSD 3-Clause License
License-File: LICENSE
Keywords: browser,jupyter,jupyterlab,jupyterlite,notebook,pyodide
Classifier: Framework :: Jupyter
Classifier: Framework :: Jupyter :: JupyterLab
Classifier: Framework :: Jupyter :: JupyterLab :: 4
Classifier: License :: OSI Approved :: BSD License
Classifier: Programming Language :: Python
Classifier: Programming Language :: Python :: 3
Classifier: Programming Language :: Python :: 3.9
Classifier: Programming Language :: Python :: 3.10
Classifier: Programming Language :: Python :: 3.11
Classifier: Programming Language :: Python :: 3.12
Classifier: Programming Language :: Python :: 3.13
Requires-Python: >=3.9
Requires-Dist: jupyterlite-core<0.7.0,>=0.6.0
Requires-Dist: pkginfo
Provides-Extra: dev
Requires-Dist: build; extra == 'dev'
Requires-Dist: hatch; extra == 'dev'
Requires-Dist: jupyterlab<4.5.0a0,>=4.4.3; extra == 'dev'
Provides-Extra: docs
Requires-Dist: ipywidgets<9,>=8.1.3; extra == 'docs'
Requires-Dist: jupyter-server-mathjax; extra == 'docs'
Requires-Dist: jupyterlab-language-pack-fr-fr; extra == 'docs'
Requires-Dist: jupyterlab-language-pack-zh-cn; extra == 'docs'
Requires-Dist: libarchive-c; extra == 'docs'
Requires-Dist: myst-parser; extra == 'docs'
Requires-Dist: pydata-sphinx-theme; extra == 'docs'
Requires-Dist: sphinx-copybutton; extra == 'docs'
Provides-Extra: lint
Requires-Dist: ruff>=0.3.0; extra == 'lint'
Provides-Extra: test
Requires-Dist: pytest; extra == 'test'
Requires-Dist: pytest-console-scripts>=1.4.0; extra == 'test'
Requires-Dist: pytest-cov; extra == 'test'
Requires-Dist: pytest-html; extra == 'test'
